alphaforge-1.0.0.dist-info/METADATA
alphaforge-1.0.0.dist-info/WHEEL
alphaforge-1.0.0.dist-info/licenses/AUTHORS.md
alphaforge/__init__.py
alphaforge/_core.cp313-win_amd64.pyd
alphaforge/core/__init__.py
alphaforge-1.0.0.dist-info/RECORD
