Metadata-Version: 2.4
Name: alphaforge
Version: 1.0.0
Classifier: Development Status :: 5 - Production/Stable
Classifier: Intended Audience :: Developers
Classifier: Intended Audience :: Financial and Insurance Industry
Classifier: License :: OSI Approved :: MIT License
Classifier: Operating System :: OS Independent
Classifier: Programming Language :: Python :: 3
Classifier: Programming Language :: Python :: 3.8
Classifier: Programming Language :: Python :: 3.9
Classifier: Programming Language :: Python :: 3.10
Classifier: Programming Language :: Python :: 3.11
Classifier: Programming Language :: Python :: 3.12
Classifier: Programming Language :: Rust
Classifier: Topic :: Office/Business :: Financial
Classifier: Topic :: Scientific/Engineering
Classifier: Topic :: Software Development :: Libraries :: Python Modules
Requires-Dist: numpy>=1.21.0
Requires-Dist: pandas>=1.3.0
Requires-Dist: msgpack>=1.0.0
Requires-Dist: pytest>=7.0.0 ; extra == 'dev'
Requires-Dist: pytest-asyncio>=0.20.0 ; extra == 'dev'
Requires-Dist: pytest-cov>=4.0.0 ; extra == 'dev'
Requires-Dist: pytest-benchmark>=4.0.0 ; extra == 'dev'
Requires-Dist: mypy>=1.0.0 ; extra == 'dev'
Requires-Dist: ruff>=0.1.0 ; extra == 'dev'
Requires-Dist: pre-commit>=3.0.0 ; extra == 'dev'
Requires-Dist: build>=0.10.0 ; extra == 'dev'
Requires-Dist: twine>=4.0.0 ; extra == 'dev'
Requires-Dist: maturin>=1.0.0 ; extra == 'dev'
Requires-Dist: mkdocs>=1.5.0 ; extra == 'docs'
Requires-Dist: mkdocs-material>=9.0.0 ; extra == 'docs'
Requires-Dist: mkdocs-git-revision-date-localized-plugin>=1.2.0 ; extra == 'docs'
Requires-Dist: pytest>=7.0.0 ; extra == 'test'
Requires-Dist: pytest-asyncio>=0.20.0 ; extra == 'test'
Requires-Dist: pytest-cov>=4.0.0 ; extra == 'test'
Requires-Dist: pytest-benchmark>=4.0.0 ; extra == 'test'
Requires-Dist: pytest-xdist>=3.0.0 ; extra == 'test'
Requires-Dist: matplotlib>=3.5.0 ; extra == 'performance'
Requires-Dist: seaborn>=0.11.0 ; extra == 'performance'
Requires-Dist: jupyter>=1.0.0 ; extra == 'performance'
Provides-Extra: dev
Provides-Extra: docs
Provides-Extra: test
Provides-Extra: performance
License-File: AUTHORS.md
Summary: High-performance algorithmic trading platform created by Krishna Bajpai and Vedanshi Gupta
Keywords: trading,algorithmic,finance,high-frequency,market-data,execution,backtesting,rust,python,quantitative,hft,low-latency
Author-email: Krishna Bajpai <krishna@krishnabajpai.me>, Vedanshi Gupta <vedanshigupta158@gmail.com>
Maintainer-email: Krishna Bajpai <krishna@krishnabajpai.me>, Vedanshi Gupta <vedanshigupta158@gmail.com>
License: MIT
Requires-Python: >=3.8
Project-URL: Homepage, https://github.com/krish567366/AlphaForge
Project-URL: Bug Reports, https://github.com/krish567366/AlphaForge/issues
Project-URL: Source, https://github.com/krish567366/AlphaForge
Project-URL: Documentation, https://github.com/krish567366/AlphaForge/blob/main/docs
Project-URL: Changelog, https://github.com/krish567366/AlphaForge/blob/main/CHANGELOG.md
